{
  "generator-jhipster": {
    "applicationType": "monolith",
    "gitHubOrganization": "mirchiseth",
    "baseName": "jhtek",
    "packageName": "io.github.jhipster.application",
    "serverPort": 8080,
    "serviceDiscoveryType": false,
    "authenticationType": "jwt",
    "uaaBaseName": "../uaa",
    "cacheProvider": "ehcache",
    "enableHibernateCache": true,
    "websocket": false,
    "databaseType": "sql",
    "devDatabaseType": "h2Disk",
    "prodDatabaseType": "postgresql",
    "searchEngine": false,
    "enableSwaggerCodegen": false,
    "messageBroker": false,
    "buildTool": "maven",
    "enableSocialSignIn": false,
    "useSass": false,
    "clientPackageManager": "yarn",
    "testFrameworks": [],
    "enableTranslation": false,
    "nativeLanguage": "en",
    "languages": [
      "en"
    ],
    "clientFramework": "angularX",
    "jhipsterVersion": "4.14.4",
    "packageFolder": "io/github/jhipster/application",
    "jwtSecretKey": "d3eaad83f103a646d044b44616b23a08f0fb4d4d",
    "jhiPrefix": "jhi"
  }
}